LICENSE
README.md
pyproject.toml
setup.cfg
txcelery/__init__.py
txcelery/defer.py
txcelery_py3.egg-info/PKG-INFO
txcelery_py3.egg-info/SOURCES.txt
txcelery_py3.egg-info/dependency_links.txt
txcelery_py3.egg-info/requires.txt
txcelery_py3.egg-info/top_level.txt